{
  "timestamp": "2026-01-20 22:00:00",
  "weibo": [
    {
      "platform": "weibo",
      "keyword": "轧戏大结局",
      "rank": 1,
      "hot": 1098036
    },
    {
      "platform": "weibo",
      "keyword": "中国乒协确认国家队教练员名单",
      "rank": 2,
      "hot": 801144
    },
    {
      "platform": "weibo",
      "keyword": "还有不到30天过年",
      "rank": 3,
      "hot": 771648
    },
    {
      "platform": "weibo",
      "keyword": "天猫年货精选周开卖",
      "rank": 4,
      "hot": 760395
    },
    {
      "platform": "weibo",
      "keyword": "代旭演技",
      "rank": 5,
      "hot": 757581
    },
    {
      "platform": "weibo",
      "keyword": "知情人称贝克汉姆夫妇深受打击",
      "rank": 6,
      "hot": 753809
    },
    {
      "platform": "weibo",
      "keyword": "肯德基下乡",
      "rank": 7,
      "hot": 752434
    },
    {
      "platform": "weibo",
      "keyword": "天猫榜单年度畅销榜权威发布",
      "rank": 8,
      "hot": 330450
    },
    {
      "platform": "weibo",
      "keyword": "解放军演练斩首行动台独慌了",
      "rank": 9,
      "hot": 288715
    },
    {
      "platform": "weibo",
      "keyword": "慕胥辞招商",
      "rank": 10,
      "hot": 212999
    },
    {
      "platform": "weibo",
      "keyword": "人类对牛奶的开发不足1%",
      "rank": 11,
      "hot": 210988
    },
    {
      "platform": "weibo",
      "keyword": "BLG战胜IG",
      "rank": 12,
      "hot": 208263
    },
    {
      "platform": "weibo",
      "keyword": "李亚鹏谈4000万欠款的真实原因",
      "rank": 13,
      "hot": 201728
    },
    {
      "platform": "weibo",
      "keyword": "向涵之瘦下来好像钟楚曦",
      "rank": 14,
      "hot": 199854
    },
    {
      "platform": "weibo",
      "keyword": "女子洗澡忘关水阀将小区变溜冰场",
      "rank": 15,
      "hot": 193282
    },
    {
      "platform": "weibo",
      "keyword": "成龙第一次参加时装周的样子",
      "rank": 16,
      "hot": 190619
    },
    {
      "platform": "weibo",
      "keyword": "肖战他瞅了我一眼",
      "rank": 17,
      "hot": 186206
    },
    {
      "platform": "weibo",
      "keyword": "女子遭强奸被杀2次望判凶手死刑",
      "rank": 18,
      "hot": 184329
    },
    {
      "platform": "weibo",
      "keyword": "何宣林回应",
      "rank": 19,
      "hot": 181605
    },
    {
      "platform": "weibo",
      "keyword": "巴奴向嫣然医院捐赠100万",
      "rank": 20,
      "hot": 178367
    },
    {
      "platform": "weibo",
      "keyword": "Turbo5Max五年电池保",
      "rank": 21,
      "hot": 175328
    },
    {
      "platform": "weibo",
      "keyword": "蹲蹲Jonathan迪奥冬季男装首秀",
      "rank": 22,
      "hot": 172913
    },
    {
      "platform": "weibo",
      "keyword": "腾讯力挺陈星旭",
      "rank": 23,
      "hot": 171784
    },
    {
      "platform": "weibo",
      "keyword": "关晓彤造型师去哪儿进修了",
      "rank": 24,
      "hot": 168762
    },
    {
      "platform": "weibo",
      "keyword": "10月大男婴被母亲扎数百针",
      "rank": 25,
      "hot": 160581
    },
    {
      "platform": "weibo",
      "keyword": "小城大事收视第一",
      "rank": 26,
      "hot": 158292
    },
    {
      "platform": "weibo",
      "keyword": "VOGUE发了王橹杰穆祉丞",
      "rank": 27,
      "hot": 135669
    },
    {
      "platform": "weibo",
      "keyword": "以为会长胖但巨减肥的习惯",
      "rank": 28,
      "hot": 114580
    },
    {
      "platform": "weibo",
      "keyword": "张维伊的演技被低估了",
      "rank": 29,
      "hot": 112958
    },
    {
      "platform": "weibo",
      "keyword": "你觉得不好看其实超健康的特点",
      "rank": 30,
      "hot": 109375
    },
    {
      "platform": "weibo",
      "keyword": "初中生网购侵华日军信件初步鉴定为真",
      "rank": 31,
      "hot": 102225
    },
    {
      "platform": "weibo",
      "keyword": "停用手机号被他人启用登上了自己微信",
      "rank": 32,
      "hot": 99648
    },
    {
      "platform": "weibo",
      "keyword": "你以为的双胞胎vs实际上的双胞胎",
      "rank": 33,
      "hot": 98957
    },
    {
      "platform": "weibo",
      "keyword": "轧戏直播",
      "rank": 34,
      "hot": 97431
    },
    {
      "platform": "weibo",
      "keyword": "女生回应张凌赫曾是补习老师",
      "rank": 35,
      "hot": 91582
    },
    {
      "platform": "weibo",
      "keyword": "王昭君灯塔水母主题皮肤",
      "rank": 36,
      "hot": 90548
    },
    {
      "platform": "weibo",
      "keyword": "12岁女孩被3人性侵陷入抑郁",
      "rank": 37,
      "hot": 89346
    },
    {
      "platform": "weibo",
      "keyword": "轧戏编剧",
      "rank": 38,
      "hot": 89138
    },
    {
      "platform": "weibo",
      "keyword": "王子奇权臣骨观音相",
      "rank": 39,
      "hot": 87793
    },
    {
      "platform": "weibo",
      "keyword": "男子去菜地偷亿点儿葱主人怒报警",
      "rank": 40,
      "hot": 86433
    },
    {
      "platform": "weibo",
      "keyword": "U23亚洲杯日本vs韩国",
      "rank": 41,
      "hot": 82924
    },
    {
      "platform": "weibo",
      "keyword": "男子在未开发区域骑马被水冲走溺亡",
      "rank": 42,
      "hot": 82409
    },
    {
      "platform": "weibo",
      "keyword": "陈哲远妈生颜霸",
      "rank": 43,
      "hot": 82299
    },
    {
      "platform": "weibo",
      "keyword": "爸爸让女儿宣传公司",
      "rank": 44,
      "hot": 82035
    },
    {
      "platform": "weibo",
      "keyword": "误食鞭炮婴儿食管里还有钉子",
      "rank": 45,
      "hot": 80832
    },
    {
      "platform": "weibo",
      "keyword": "嫣然医院将暂时谢绝到访参观",
      "rank": 46,
      "hot": 78323
    },
    {
      "platform": "weibo",
      "keyword": "利欧股份股票复牌",
      "rank": 47,
      "hot": 77443
    },
    {
      "platform": "weibo",
      "keyword": "裴轸爱到最后身后空无一物",
      "rank": 48,
      "hot": 77428
    },
    {
      "platform": "weibo",
      "keyword": "代旭红秀采访",
      "rank": 49,
      "hot": 77207
    },
    {
      "platform": "weibo",
      "keyword": "南京一车主雪天把车开上墙",
      "rank": 50,
      "hot": 76102
    },
    {
      "platform": "weibo",
      "keyword": "小米汽车通报",
      "rank": 51,
      "hot": 75186
    },
    {
      "platform": "weibo",
      "keyword": "多家银行卫星近期集中上天",
      "rank": 52,
      "hot": 74435
    }
  ],
  "douyin": [
    {
      "platform": "douyin",
      "keyword": "U23亚洲杯中国对阵越南",
      "rank": 1,
      "hot": 12101472
    },
    {
      "platform": "douyin",
      "keyword": "马年非遗祈福百景图",
      "rank": 2,
      "hot": 11643415
    },
    {
      "platform": "douyin",
      "keyword": "数读2025年中国经济成绩单",
      "rank": 3,
      "hot": 11468087
    },
    {
      "platform": "douyin",
      "keyword": "第一批雪人已经卷起来了",
      "rank": 4,
      "hot": 11451353
    },
    {
      "platform": "douyin",
      "keyword": "外面漫天飞雪正是涮肉的时节",
      "rank": 5,
      "hot": 10681754
    },
    {
      "platform": "douyin",
      "keyword": "年末高光穿搭大赏",
      "rank": 6,
      "hot": 10458904
    },
    {
      "platform": "douyin",
      "keyword": "跟着各地年货回家寻年味",
      "rank": 7,
      "hot": 9347838
    },
    {
      "platform": "douyin",
      "keyword": "在盛典一次性嗑到3对短剧CP",
      "rank": 8,
      "hot": 9276592
    },
    {
      "platform": "douyin",
      "keyword": "冯德莱恩：格陵兰岛主权不容谈判",
      "rank": 9,
      "hot": 8945988
    },
    {
      "platform": "douyin",
      "keyword": "许金花被执行死刑",
      "rank": 10,
      "hot": 8201269
    },
    {
      "platform": "douyin",
      "keyword": "大寒开启滑雪人狂欢模式",
      "rank": 11,
      "hot": 7900264
    },
    {
      "platform": "douyin",
      "keyword": "四川殴打5人者有“特殊背景”不实",
      "rank": 12,
      "hot": 7828663
    },
    {
      "platform": "douyin",
      "keyword": "U23亚洲杯日本1:0韩国",
      "rank": 13,
      "hot": 7805273
    },
    {
      "platform": "douyin",
      "keyword": "杭州终于等来了雪",
      "rank": 14,
      "hot": 7805015
    },
    {
      "platform": "douyin",
      "keyword": "欧洲酝酿对美“放大招”",
      "rank": 15,
      "hot": 7798077
    },
    {
      "platform": "douyin",
      "keyword": "苏州一下雪就美成了姑苏",
      "rank": 16,
      "hot": 7792363
    },
    {
      "platform": "douyin",
      "keyword": "著名相声表演艺术家杨振华逝世",
      "rank": 17,
      "hot": 7791441
    },
    {
      "platform": "douyin",
      "keyword": "娜娜米手势舞挑战",
      "rank": 18,
      "hot": 7790514
    },
    {
      "platform": "douyin",
      "keyword": "轧戏大结局",
      "rank": 19,
      "hot": 7782503
    },
    {
      "platform": "douyin",
      "keyword": "梁小龙死因公开：因心脏衰竭离世",
      "rank": 20,
      "hot": 7771900
    },
    {
      "platform": "douyin",
      "keyword": "特朗普称英“愚蠢至极”",
      "rank": 21,
      "hot": 7770443
    },
    {
      "platform": "douyin",
      "keyword": "欧盟决定永久冻结俄罗斯资产",
      "rank": 22,
      "hot": 7765815
    },
    {
      "platform": "douyin",
      "keyword": "巴特勒赛季报销",
      "rank": 23,
      "hot": 7748212
    },
    {
      "platform": "douyin",
      "keyword": "突然的喜欢定档",
      "rank": 24,
      "hot": 7745473
    },
    {
      "platform": "douyin",
      "keyword": "手搓粉彩风转场来了",
      "rank": 25,
      "hot": 7745454
    },
    {
      "platform": "douyin",
      "keyword": "永州队5:0大胜哈尔滨队",
      "rank": 26,
      "hot": 7742235
    },
    {
      "platform": "douyin",
      "keyword": "网传“蛇窝蹦迪”的视频可信吗",
      "rank": 27,
      "hot": 7735875
    },
    {
      "platform": "douyin",
      "keyword": "温太医你是这样上凌云峰的吗",
      "rank": 28,
      "hot": 7735149
    },
    {
      "platform": "douyin",
      "keyword": "今年的冬天没有遗憾啦",
      "rank": 29,
      "hot": 7730685
    },
    {
      "platform": "douyin",
      "keyword": "王玉雯新剧就这样手搓抖音",
      "rank": 30,
      "hot": 7730385
    },
    {
      "platform": "douyin",
      "keyword": "用这首病态的爱发什么都很配",
      "rank": 31,
      "hot": 7726398
    },
    {
      "platform": "douyin",
      "keyword": "车澈自曝瘦了68斤",
      "rank": 32,
      "hot": 7724277
    },
    {
      "platform": "douyin",
      "keyword": "遇到讨厌的人我们换个说法",
      "rank": 33,
      "hot": 7720874
    },
    {
      "platform": "douyin",
      "keyword": "左奇函高富帅变装",
      "rank": 34,
      "hot": 7719427
    },
    {
      "platform": "douyin",
      "keyword": "深空初雪与爱人相拥",
      "rank": 35,
      "hot": 7717386
    },
    {
      "platform": "douyin",
      "keyword": "下了雪的紫金山美若仙境",
      "rank": 36,
      "hot": 7715937
    },
    {
      "platform": "douyin",
      "keyword": "徐良官宣巡演",
      "rank": 37,
      "hot": 7715108
    },
    {
      "platform": "douyin",
      "keyword": "长沙2026第一场雪",
      "rank": 38,
      "hot": 7697827
    },
    {
      "platform": "douyin",
      "keyword": "海昌企鹅冬日限定遛弯萌化了",
      "rank": 39,
      "hot": 7696006
    },
    {
      "platform": "douyin",
      "keyword": "赵丽颖：属于李秋萍的落笔生辉",
      "rank": 40,
      "hot": 7688175
    },
    {
      "platform": "douyin",
      "keyword": "大表哥银杏湖巨物捕捞行动",
      "rank": 41,
      "hot": 7686754
    },
    {
      "platform": "douyin",
      "keyword": "大瑶出演东北警察故事3",
      "rank": 42,
      "hot": 7684800
    },
    {
      "platform": "douyin",
      "keyword": "这是连续剧草莓恨恨恨吗",
      "rank": 43,
      "hot": 7681099
    },
    {
      "platform": "douyin",
      "keyword": "关晓彤黑礼帽暗夜女王",
      "rank": 44,
      "hot": 7680325
    },
    {
      "platform": "douyin",
      "keyword": "电影镖人集齐四代武侠人",
      "rank": 45,
      "hot": 7674741
    },
    {
      "platform": "douyin",
      "keyword": "我的漂亮藏不住了",
      "rank": 46,
      "hot": 7674739
    },
    {
      "platform": "douyin",
      "keyword": "咪的步伐很曼妙",
      "rank": 47,
      "hot": 7673058
    },
    {
      "platform": "douyin",
      "keyword": "上海几乎年年下雪为何难被看见",
      "rank": 48,
      "hot": 7671316
    },
    {
      "platform": "douyin",
      "keyword": "都暻秀为何这样跳Crown",
      "rank": 49,
      "hot": 7670517
    }
  ]
}